{
  "flow_name": "praise_t_article_tasks",
  "flow_subtype": "generated",
  "flow_type": "data_list",
  "rows": [
    {
      "id": "relax_17",
      "lottie_asset": "lottie/relax/looping_rings.json",
      "media_asset": "audio/relax/relax_17.mp3",
      "media_type": "audio",
      "title": "Praise yourself",
      "_translations": {
        "title": {},
        "transcript": {
          "tz_sw": true
        }
      },
      "_translatedFields": {
        "title": {
          "eng": "Praise yourself"
        },
        "transcript": {
          "eng": "Self-praise can be really helpful, especially when we have difficult days. \n\nThink of your week and finish the following phrase: “This week, I am proud of myself for …” It can be anything, not just things about being a parent!\n\nThink of one thing you did well today. Now wrap your arms around yourself and give yourself a big HUG!"
        }
      },
      "transcript": "Self-praise can be really helpful, especially when we have difficult days. \n\nThink of your week and finish the following phrase: “This week, I am proud of myself for …” It can be anything, not just things about being a parent!\n\nThink of one thing you did well today. Now wrap your arms around yourself and give yourself a big HUG!",
      "category_id": "relax",
      "nested": false,
      "completed": false
    },
    {
      "id": "check_in_3",
      "attached_single_doc": "https://docs.google.com/document/d/1weBDi-7Z101TP408tO48rWUM3m75TIrW5KMnEDOeB9c",
      "_translatedFields": {
        "text_1": {
          "eng": "You matter! Take a moment to check in with yourself."
        },
        "quiz_1_feedback_1": {
          "eng": "Great to hear that you are doing well. You are a wonderful parent!"
        },
        "quiz_1_feedback_2": {
          "eng": "Sorry that you are not having the best day. Well done for trying to figure everything out. Nobody has all the answers but you really do your best!"
        },
        "quiz_1_feedback_3": {
          "eng": "Sorry to hear that you are not having a good day. Well done for getting up every morning and trying again, even when you are tired. That is real courage and dedication!"
        },
        "quiz_1_question": {
          "eng": "How are you feeling today?"
        },
        "quiz_1_option_1_text": {
          "eng": "Happy"
        },
        "quiz_1_option_2_text": {
          "eng": "Okay"
        },
        "quiz_1_option_3_text": {
          "eng": "Sad"
        }
      },
      "category_id": "check_in",
      "nested": false,
      "quiz_1_option_1_image_asset": "images/icons/faces/happy_face_new.svg",
      "quiz_1_option_2_image_asset": "images/icons/faces/ok_face_new.svg",
      "quiz_1_option_3_image_asset": "images/icons/faces/sad_face_new.svg",
      "text_1": "You matter! Take a moment to check in with yourself.",
      "_translations": {
        "text_1": {
          "tz_sw": true
        },
        "quiz_1_feedback_1": {
          "tz_sw": true
        },
        "quiz_1_feedback_2": {
          "tz_sw": true
        },
        "quiz_1_feedback_3": {
          "tz_sw": true
        },
        "quiz_1_question": {
          "tz_sw": true
        },
        "quiz_1_option_1_text": {
          "tz_sw": true
        },
        "quiz_1_option_2_text": {
          "tz_sw": true
        },
        "quiz_1_option_3_text": {
          "tz_sw": true
        }
      },
      "quiz_1_feedback_1": "Great to hear that you are doing well. You are a wonderful parent!",
      "quiz_1_feedback_2": "Sorry that you are not having the best day. Well done for trying to figure everything out. Nobody has all the answers but you really do your best!",
      "quiz_1_feedback_3": "Sorry to hear that you are not having a good day. Well done for getting up every morning and trying again, even when you are tired. That is real courage and dedication!",
      "quiz_1_question": "How are you feeling today?",
      "quiz_1_option_1_text": "Happy",
      "quiz_1_option_2_text": "Okay",
      "quiz_1_option_3_text": "Sad",
      "completed": false
    },
    {
      "id": "intro_1",
      "media_asset": "/audio/teen/topic_intros/praise_intro_t.mp3",
      "media_type": "audio",
      "attached_single_doc": "https://docs.google.com/document/d/10juxGUlCjuBe9RxlMtsk9d-IovhNamMky1PVQ4EyIh0",
      "_translatedFields": {
        "text_1_facilitator": {
          "eng": "Today's topic is about praise.\n\nPraise is a powerful parenting skill.\n\nIf we praise our teens when they do something well, we will see them do more and more positive things!"
        },
        "media_title": {
          "eng": "How will praise help you and your family? Tap play to find out!"
        },
        "media_transcript": {
          "eng": "Greetings everyone.\n\nOur topic today is about praise.\n\nIt is good to praise our children when they've done good because when we do that, they will do more of that good behavior we want to see.\n\nAnd let's not forget to praise ourselves when we do good!"
        }
      },
      "category_id": "intro",
      "nested": false,
      "text_1_facilitator": "Today's topic is about praise.\n\nPraise is a powerful parenting skill.\n\nIf we praise our teens when they do something well, we will see them do more and more positive things!",
      "_translations": {
        "text_1_facilitator": {},
        "media_title": {},
        "media_transcript": {}
      },
      "media_title": "How will praise help you and your family? Tap play to find out!",
      "media_transcript": "Greetings everyone.\n\nOur topic today is about praise.\n\nIt is good to praise our children when they've done good because when we do that, they will do more of that good behavior we want to see.\n\nAnd let's not forget to praise ourselves when we do good!",
      "completed": false
    },
    {
      "id": "intro_2",
      "media_asset": "/audio/teen/testimonials/caregiver/caregiver_test_praise_t.mp3",
      "media_type": "audio",
      "attached_single_doc": "https://docs.google.com/document/d/10juxGUlCjuBe9RxlMtsk9d-IovhNamMky1PVQ4EyIh0",
      "_translatedFields": {
        "text_1_facilitator": {
          "eng": "Praise is an easy way to build your teen’s confidence and strengthen your connection. It really works!"
        },
        "media_title": {
          "eng": "Praise works, but it’s not always easy. Hear how @data.characters.media_female_2.name started using it at home"
        },
        "media_transcript": {
          "eng": "When we learnt about this praising thing I thought, “We were never praised for things as teenagers, so why should we start now?” But I got interested when I learnt what the benefits of praising could be.\n\nRight after the weekly workshop, I noticed my teen doing what they do every day: washing the dishes. And I said “Thank you for washing the dishes, my girl, it really makes me happy that you are helping out.” My teen was smiling and she even came to give me a hug, which she never does.\n\nThis praising business is hard. I still forget sometimes or give praise at the same time as criticism. But praising really makes a difference. I never thought that a simple praise could make such a change in a person!"
        }
      },
      "category_id": "intro",
      "nested": false,
      "text_1_facilitator": "Praise is an easy way to build your teen’s confidence and strengthen your connection. It really works!",
      "_translations": {
        "text_1_facilitator": {},
        "media_title": {},
        "media_transcript": {}
      },
      "media_title": "Praise works, but it’s not always easy. Hear how @data.characters.media_female_2.name started using it at home",
      "media_transcript": "When we learnt about this praising thing I thought, “We were never praised for things as teenagers, so why should we start now?” But I got interested when I learnt what the benefits of praising could be.\n\nRight after the weekly workshop, I noticed my teen doing what they do every day: washing the dishes. And I said “Thank you for washing the dishes, my girl, it really makes me happy that you are helping out.” My teen was smiling and she even came to give me a hug, which she never does.\n\nThis praising business is hard. I still forget sometimes or give praise at the same time as criticism. But praising really makes a difference. I never thought that a simple praise could make such a change in a person!",
      "completed": false
    },
    {
      "id": "explore_1",
      "attached_single_doc": "https://docs.google.com/document/d/10juxGUlCjuBe9RxlMtsk9d-IovhNamMky1PVQ4EyIh0",
      "_translatedFields": {
        "text_1_facilitator": {
          "eng": "Let’s reflect on our own experience with praise."
        },
        "quiz_1_question": {
          "eng": "Think about the last time someone thanked you, or said you did something great.\n\nHow did it make you feel?"
        },
        "quiz_1_option_1_text": {
          "eng": "Okay"
        },
        "quiz_1_feedback_1": {
          "eng": "We sometimes have to get used to being praised and praising others. That’s okay."
        },
        "quiz_1_option_2_text": {
          "eng": "Happy"
        },
        "quiz_1_feedback_2": {
          "eng": "That's great! Being praised often makes us feel happy."
        },
        "quiz_1_option_3_text": {
          "eng": "Proud"
        },
        "quiz_1_feedback_3": {
          "eng": "That’s great! Being praised often makes us feel proud."
        },
        "quiz_2_question": {
          "eng": "Parents usually do not get thanked or praised enough.\n\nHow does it make you feel when nobody says \"thank you\"?"
        },
        "quiz_2_option_1_text": {
          "eng": "Sad"
        },
        "quiz_2_feedback_1": {
          "eng": "Your teen can feel this way too. That's what makes this week's parenting tool simple but important: Praise them for what they do right."
        },
        "quiz_2_option_2_text": {
          "eng": "Angry"
        },
        "quiz_2_feedback_2": {
          "eng": "Your teen can feel this way too. That's what makes this week's parenting tool simple but important: Praise them for what they do right."
        },
        "quiz_2_option_3_text": {
          "eng": "Tired"
        },
        "quiz_2_feedback_3": {
          "eng": "Your teen can feel this way too. That's what makes this week's parenting tool simple but important: Praise them for what they do right."
        }
      },
      "category_id": "explore",
      "nested": false,
      "quiz_1_option_1_image_asset": "images/faces/neutral.svg",
      "quiz_1_option_2_image_asset": "images/faces/happy.svg",
      "quiz_1_option_3_image_asset": "images/faces/happiest.svg",
      "quiz_1_feedback_1": "We sometimes have to get used to being praised and praising others. That’s okay.",
      "_translations": {
        "quiz_1_feedback_1": {},
        "quiz_1_feedback_2": {},
        "quiz_1_feedback_3": {},
        "quiz_1_question": {},
        "quiz_1_option_1_text": {
          "tz_sw": true
        },
        "quiz_1_option_2_text": {
          "tz_sw": true
        },
        "quiz_1_option_3_text": {},
        "text_1_facilitator": {},
        "quiz_2_question": {},
        "quiz_2_option_1_text": {
          "tz_sw": true
        },
        "quiz_2_feedback_1": {},
        "quiz_2_option_2_text": {
          "tz_sw": true
        },
        "quiz_2_feedback_2": {},
        "quiz_2_option_3_text": {
          "tz_sw": true
        },
        "quiz_2_feedback_3": {}
      },
      "quiz_1_feedback_2": "That's great! Being praised often makes us feel happy.",
      "quiz_1_feedback_3": "That’s great! Being praised often makes us feel proud.",
      "quiz_1_question": "Think about the last time someone thanked you, or said you did something great.\n\nHow did it make you feel?",
      "quiz_1_option_1_text": "Okay",
      "quiz_1_option_2_text": "Happy",
      "quiz_1_option_3_text": "Proud",
      "text_1_facilitator": "Let’s reflect on our own experience with praise.",
      "quiz_2_option_1_image_asset": "images/faces/sad.svg",
      "quiz_2_option_2_image_asset": "images/faces/angry.svg",
      "quiz_2_option_3_image_asset": "images/faces/tired.svg",
      "quiz_2_question": "Parents usually do not get thanked or praised enough.\n\nHow does it make you feel when nobody says \"thank you\"?",
      "quiz_2_option_1_text": "Sad",
      "quiz_2_feedback_1": "Your teen can feel this way too. That's what makes this week's parenting tool simple but important: Praise them for what they do right.",
      "quiz_2_option_2_text": "Angry",
      "quiz_2_feedback_2": "Your teen can feel this way too. That's what makes this week's parenting tool simple but important: Praise them for what they do right.",
      "quiz_2_option_3_text": "Tired",
      "quiz_2_feedback_3": "Your teen can feel this way too. That's what makes this week's parenting tool simple but important: Praise them for what they do right.",
      "completed": false
    },
    {
      "id": "explore_2",
      "attached_single_doc": "https://docs.google.com/document/d/10juxGUlCjuBe9RxlMtsk9d-IovhNamMky1PVQ4EyIh0",
      "_translatedFields": {
        "text_1_facilitator": {
          "eng": "Just like we feel better when praised, teens do too. Let’s look at a simple example with @data.characters.f1_father.name and his son, @data.characters.f1_son_14.name."
        },
        "character_1_text": {
          "eng": "Thank you for doing the dishes, @data.characters.f1_son_14.name. It's a big help!"
        },
        "character_2_text": {
          "eng": "@data.characters.f1_father_role.name, I hate doing the dishes every day. It is women’s work! @data.characters.f1_mother_role.name or @data.characters.f1_daughter_16.name should be doing them. Even my book at school only shows women doing the dishes."
        }
      },
      "category_id": "explore",
      "nested": false,
      "text_1_facilitator": "Just like we feel better when praised, teens do too. Let’s look at a simple example with @data.characters.f1_father.name and his son, @data.characters.f1_son_14.name.",
      "_translations": {
        "text_1_facilitator": {},
        "character_1_text": {},
        "character_2_text": {}
      },
      "image_asset": "/images/teen_modules/praise/praise1_t_2.svg",
      "character_1_id": "f1_father",
      "character_2_id": "f1_son_14",
      "character_1_text": "Thank you for doing the dishes, @data.characters.f1_son_14.name. It's a big help!",
      "character_2_text": "@data.characters.f1_father_role.name, I hate doing the dishes every day. It is women’s work! @data.characters.f1_mother_role.name or @data.characters.f1_daughter_16.name should be doing them. Even my book at school only shows women doing the dishes.",
      "completed": false
    },
    {
      "id": "explore_3",
      "attached_single_doc": "https://docs.google.com/document/d/10juxGUlCjuBe9RxlMtsk9d-IovhNamMky1PVQ4EyIh0",
      "_translatedFields": {
        "character_1_text": {
          "eng": "It is not women’s work. @data.characters.f1_mother_role.name and @data.characters.f1_daughter_16.name  are busy at work and school all day as well. We all need to play our part at home too."
        },
        "character_2_text": {
          "eng": "Whatever *you* say."
        }
      },
      "category_id": "explore",
      "nested": false,
      "image_asset": "/images/teen_modules/praise/praise1_t_2.svg",
      "character_1_id": "f1_father",
      "character_2_id": "f1_son_14",
      "character_1_text": "It is not women’s work. @data.characters.f1_mother_role.name and @data.characters.f1_daughter_16.name  are busy at work and school all day as well. We all need to play our part at home too.",
      "_translations": {
        "character_1_text": {},
        "character_2_text": {}
      },
      "character_2_text": "Whatever *you* say.",
      "completed": false
    },
    {
      "id": "explore_4",
      "attached_single_doc": "https://docs.google.com/document/d/10juxGUlCjuBe9RxlMtsk9d-IovhNamMky1PVQ4EyIh0",
      "_translatedFields": {
        "character_1_text": {
          "eng": "I know it's hard to understand, but it's important that we all work together. Doing this kind of work will help you become an independent and responsible man when you have your own family. \n\nI am proud of you for doing your part. Here, let me help you dry the dishes."
        },
        "character_2_text": {
          "eng": "Thanks for helping me @data.characters.f1_father_role.name."
        },
        "quiz_1_question": {
          "eng": "Why did @data.characters.f1_father.name’s praise help @data.characters.f1_son_14.name?"
        },
        "quiz_1_option_1_text": {
          "eng": "It made @data.characters.f1_son_14.name feel seen and appreciated"
        },
        "quiz_1_feedback_1": {
          "eng": "Exactly! Praise helps teens feel valued, and they are more likely to help again."
        },
        "quiz_1_option_2_text": {
          "eng": "It helped @data.characters.f1_son_14.name feel respected and more willing to help again"
        },
        "quiz_1_feedback_2": {
          "eng": "Exactly! Praise helps teens feel valued, and they are more likely to help again."
        },
        "quiz_1_option_3_text": {
          "eng": "It made @data.characters.f1_son_14.name feel more connected to his father"
        },
        "quiz_1_feedback_3": {
          "eng": "Exactly! Praise helps teens feel valued, and they are more likely to help again."
        }
      },
      "category_id": "explore",
      "nested": false,
      "quiz_1_feedback_1": "Exactly! Praise helps teens feel valued, and they are more likely to help again.",
      "_translations": {
        "quiz_1_feedback_1": {},
        "quiz_1_feedback_2": {},
        "quiz_1_feedback_3": {},
        "quiz_1_question": {},
        "quiz_1_option_1_text": {},
        "quiz_1_option_2_text": {},
        "quiz_1_option_3_text": {},
        "character_1_text": {},
        "character_2_text": {}
      },
      "quiz_1_feedback_2": "Exactly! Praise helps teens feel valued, and they are more likely to help again.",
      "quiz_1_feedback_3": "Exactly! Praise helps teens feel valued, and they are more likely to help again.",
      "quiz_1_question": "Why did @data.characters.f1_father.name’s praise help @data.characters.f1_son_14.name?",
      "quiz_1_option_1_text": "It made @data.characters.f1_son_14.name feel seen and appreciated",
      "quiz_1_option_2_text": "It helped @data.characters.f1_son_14.name feel respected and more willing to help again",
      "quiz_1_option_3_text": "It made @data.characters.f1_son_14.name feel more connected to his father",
      "image_asset": "/images/teen_modules/praise/praise1_t_2.svg",
      "character_1_id": "f1_father",
      "character_2_id": "f1_son_14",
      "character_1_text": "I know it's hard to understand, but it's important that we all work together. Doing this kind of work will help you become an independent and responsible man when you have your own family. \n\nI am proud of you for doing your part. Here, let me help you dry the dishes.",
      "character_2_text": "Thanks for helping me @data.characters.f1_father_role.name.",
      "completed": false
    },
    {
      "id": "tips_1",
      "attached_single_doc": "https://docs.google.com/document/d/10juxGUlCjuBe9RxlMtsk9d-IovhNamMky1PVQ4EyIh0",
      "_translatedFields": {
        "text_1_facilitator": {
          "eng": "Here are some skills to help you praise your teens.\nYou can also praise other adults in your household, too. Notice how they respond!"
        },
        "section_1_title": {
          "eng": "SEE IT"
        },
        "section_1_text": {
          "eng": "Look for anything your teen does that is helpful or good and praise them for it. They may not show it, but you will see them doing that good thing again. It will also reassure them that you notice and care."
        },
        "section_2_title": {
          "eng": "SAY IT"
        },
        "section_2_text": {
          "eng": "Be enthusiastic – really mean it when you say it!"
        },
        "section_3_title": {
          "eng": "REPEAT IT"
        },
        "section_3_text": {
          "eng": "Try to find something to thank your boys and girls for every day. Even something really small."
        },
        "section_3_button_text": {
          "eng": "More tips"
        },
        "section_3_extra_text": {
          "eng": "Remember, teens respond best to positive attention. When they feel noticed and appreciated at home, they are less likely to take risks to earn approval from others."
        }
      },
      "category_id": "practical_tips",
      "nested": false,
      "text_1_facilitator": "Here are some skills to help you praise your teens.\nYou can also praise other adults in your household, too. Notice how they respond!",
      "_translations": {
        "text_1_facilitator": {},
        "section_1_title": {},
        "section_1_text": {},
        "section_2_title": {},
        "section_2_text": {},
        "section_3_title": {},
        "section_3_text": {},
        "section_3_button_text": {},
        "section_3_extra_text": {}
      },
      "section_1_icon_asset": "images/icons/eye_blue.png",
      "section_2_icon_asset": "images/icons/single_speech_blue.png",
      "section_3_icon_asset": "images/icons/trophy_blue.png",
      "section_1_title": "SEE IT",
      "section_1_text": "Look for anything your teen does that is helpful or good and praise them for it. They may not show it, but you will see them doing that good thing again. It will also reassure them that you notice and care.",
      "section_2_title": "SAY IT",
      "section_2_text": "Be enthusiastic – really mean it when you say it!",
      "section_3_title": "REPEAT IT",
      "section_3_text": "Try to find something to thank your boys and girls for every day. Even something really small.",
      "section_3_button_text": "More tips",
      "section_3_extra_text": "Remember, teens respond best to positive attention. When they feel noticed and appreciated at home, they are less likely to take risks to earn approval from others.",
      "completed": false
    },
    {
      "id": "practise",
      "attached_single_doc": "https://docs.google.com/document/d/10juxGUlCjuBe9RxlMtsk9d-IovhNamMky1PVQ4EyIh0",
      "_translatedFields": {
        "text_1_facilitator": {
          "eng": "It can be hard to think of reasons to praise your teen! Here are some ideas from other parents:"
        },
        "text_2": {
          "eng": "**Thank you for...**\n- Being kind to someone\n- Cleaning your room\n- Joining a family meal\n- Greeting other family members\n- Looking after your siblings\n- Coming home on time\n- Showing thoughtfulness\n- Saying 'please' or 'thank you'\n- Going to school on time\n- Doing chores or schoolwork"
        }
      },
      "category_id": "practise",
      "nested": false,
      "text_1_facilitator": "It can be hard to think of reasons to praise your teen! Here are some ideas from other parents:",
      "_translations": {
        "text_1_facilitator": {},
        "text_2": {}
      },
      "text_2": "**Thank you for...**\n- Being kind to someone\n- Cleaning your room\n- Joining a family meal\n- Greeting other family members\n- Looking after your siblings\n- Coming home on time\n- Showing thoughtfulness\n- Saying 'please' or 'thank you'\n- Going to school on time\n- Doing chores or schoolwork",
      "completed": false
    },
    {
      "id": "home_activity_1",
      "attached_single_doc": "https://docs.google.com/document/d/10juxGUlCjuBe9RxlMtsk9d-IovhNamMky1PVQ4EyIh0",
      "_translatedFields": {
        "text_1_facilitator": {
          "eng": "This week’s home activity is to praise your teen once a day. It only takes a few seconds."
        },
        "quiz_1_question": {
          "eng": "Can you praise your teen once a day this week?"
        },
        "quiz_1_option_1_text": {
          "eng": "Yes"
        },
        "quiz_1_feedback_1": {
          "eng": "That's great! Parents who practise praise at home get better results!"
        },
        "quiz_1_option_2_text": {
          "eng": "I think so"
        },
        "quiz_1_feedback_2": {
          "eng": "You can do it! Try praising your teen for something simple at first, like looking after their siblings or going to school."
        },
        "quiz_1_option_3_text": {
          "eng": "No"
        },
        "quiz_1_feedback_3": {
          "eng": "That's okay. With time, giving praise will become easier. Try to praise yourself for something first, like \"Good job using @global.app_name. It shows you care.\""
        }
      },
      "category_id": "home_activity",
      "nested": false,
      "quiz_1_feedback_1": "That's great! Parents who practise praise at home get better results!",
      "_translations": {
        "quiz_1_feedback_1": {},
        "quiz_1_feedback_2": {},
        "quiz_1_feedback_3": {},
        "quiz_1_question": {},
        "quiz_1_option_1_text": {
          "tz_sw": true
        },
        "quiz_1_option_2_text": {},
        "quiz_1_option_3_text": {
          "tz_sw": true
        },
        "text_1_facilitator": {}
      },
      "quiz_1_feedback_2": "You can do it! Try praising your teen for something simple at first, like looking after their siblings or going to school.",
      "quiz_1_feedback_3": "That's okay. With time, giving praise will become easier. Try to praise yourself for something first, like \"Good job using @global.app_name. It shows you care.\"",
      "quiz_1_question": "Can you praise your teen once a day this week?",
      "quiz_1_option_1_text": "Yes",
      "quiz_1_option_2_text": "I think so",
      "quiz_1_option_3_text": "No",
      "text_1_facilitator": "This week’s home activity is to praise your teen once a day. It only takes a few seconds.",
      "completed": false
    },
    {
      "id": "teen_test_1",
      "media_asset": "/audio/teen/testimonials/teen/teen_test_praise_t.mp3",
      "media_type": "audio",
      "attached_single_doc": "https://docs.google.com/document/d/10juxGUlCjuBe9RxlMtsk9d-IovhNamMky1PVQ4EyIh0",
      "_translatedFields": {
        "text_1_facilitator": {
          "eng": "Remember, praise is a powerful tool. The more attention you give to positive behaviour, the more positive behaviour you will see."
        },
        "media_title": {
          "eng": "Hear from @data.characters.media_daughter_2.name on how it feels to get praise from her mother"
        },
        "media_transcript": {
          "eng": "I was grateful when my mother learned about praise.\n\nBefore the workshop, she mostly noticed when I did something wrong. She would shout and sometimes hit me.\n\nBut after the workshop, she began praising me for small things — even things she never noticed before, like my good maths grades. At first I thought, ‘What is going on?’ But she kept doing it. I liked it, so I started doing more good things.\n\nIt feels good that my mother now sees the good in me, not only the bad.\n\nOne day during one-on-one time, I told her, ‘Thank you, Mama, for saying something nice when I do things well, not only when I do things wrong.’ It made both of us very happy."
        }
      },
      "category_id": "teen_test",
      "nested": false,
      "text_1_facilitator": "Remember, praise is a powerful tool. The more attention you give to positive behaviour, the more positive behaviour you will see.",
      "_translations": {
        "text_1_facilitator": {},
        "media_title": {},
        "media_transcript": {}
      },
      "media_title": "Hear from @data.characters.media_daughter_2.name on how it feels to get praise from her mother",
      "media_transcript": "I was grateful when my mother learned about praise.\n\nBefore the workshop, she mostly noticed when I did something wrong. She would shout and sometimes hit me.\n\nBut after the workshop, she began praising me for small things — even things she never noticed before, like my good maths grades. At first I thought, ‘What is going on?’ But she kept doing it. I liked it, so I started doing more good things.\n\nIt feels good that my mother now sees the good in me, not only the bad.\n\nOne day during one-on-one time, I told her, ‘Thank you, Mama, for saying something nice when I do things well, not only when I do things wrong.’ It made both of us very happy.",
      "completed": false
    }
  ],
  "_metadata": {
    "nested": {
      "type": "boolean"
    },
    "completed": {
      "type": "boolean"
    }
  }
}