{
  "flow_type": "data_list",
  "flow_name": "about_this_app",
  "status": "released",
  "data_list_name": "about_this_app",
  "rows": [
    {
      "id": "text_1",
      "text": "@global.app_name is an app designed by IDEMS International and Parenting for Lifelong Health to support parents and caregivers of children 10 to 17 years of age. Illustrations are original works by Orli Setton for Parenting for Lifelong Health. All content herein is shared under a Creative Commons BY-SA International 4.0 license. It was developed in collaboration with key partners:",
      "_translations": {
        "text": {}
      },
      "_translatedFields": {
        "text": {
          "eng": "@global.app_name is an app designed by IDEMS International and Parenting for Lifelong Health to support parents and caregivers of children 10 to 17 years of age. Illustrations are original works by Orli Setton for Parenting for Lifelong Health. All content herein is shared under a Creative Commons BY-SA International 4.0 license. It was developed in collaboration with key partners:"
        }
      }
    }
  ],
  "_source": {
    "name": "teens_tz",
    "path": "data/deployment_data_tz.xlsx",
    "url": "https://docs.google.com/spreadsheets/d/1DjzYwjPkUV-meBwiePiDB00TN5zXa2l0gsSk6LU6ZNA"
  }
}