{
  "flow_name": "odk_form_talk",
  "flow_subtype": "generated",
  "flow_type": "template",
  "rows": [
    {
      "type": "template",
      "name": "odk_form",
      "value": "odk_form",
      "action_list": [
        {
          "trigger": "completed",
          "action_id": "emit",
          "args": [
            "completed"
          ],
          "_raw": "completed | emit: completed"
        },
        {
          "trigger": "uncompleted",
          "action_id": "emit",
          "args": [
            "uncompleted"
          ],
          "_raw": "uncompleted | emit: uncompleted"
        }
      ],
      "rows": [
        {
          "name": "module_id",
          "value": "talk",
          "_translations": {
            "value": {}
          },
          "type": "set_variable",
          "_nested_name": "odk_form.module_id"
        }
      ],
      "_nested_name": "odk_form"
    }
  ]
}